py_scgot-0.3.1.dist-info/licenses/LICENSE.txt
pygot/__init__.py
pygot/evalute.py
pygot/utils.py
pygot/.ipynb_checkpoints/interpolator-checkpoint.pyx
pygot/datasets/__init__.py
pygot/datasets/_datasets.py
pygot/external/__init__.py
pygot/external/_external.py
pygot/external/otcfm.py
pygot/external/palantir.py
pygot/external/parametric_umap.py
pygot/external/tigon.py
pygot/plotting/__init__.py
pygot/plotting/plot_mst.py
pygot/plotting/plot_root.py
pygot/plotting/plot_traj.py
pygot/preprocessing/__init__.py
pygot/preprocessing/_dimension_reduction.py
pygot/preprocessing/_neighbors.py
pygot/preprocessing/vis_mapper.py
pygot/tools/__init__.py
pygot/tools/analysis/TF_list.py
pygot/tools/analysis/__init__.py
pygot/tools/analysis/cell_fate.py
pygot/tools/analysis/density.py
pygot/tools/analysis/grn_inference.py
pygot/tools/analysis/oracle_utils.py
pygot/tools/analysis/utils.py
pygot/tools/traj/__init__.py
pygot/tools/traj/flow.py
pygot/tools/traj/loss_func.py
pygot/tools/traj/markov.py
pygot/tools/traj/model_training.py
pygot/tools/traj/mst.py
pygot/tools/traj/root_identify.py
pygot/tools/traj/snapshot_pipeline.py
pygot/tools/traj/utils.py
pygot/tools/traj/v_centric_training.py
pygot/tools/traj/x_centric_training.py
py_scgot-0.3.1.dist-info/METADATA
py_scgot-0.3.1.dist-info/WHEEL
py_scgot-0.3.1.dist-info/top_level.txt
py_scgot-0.3.1.dist-info/RECORD
